pronto/__init__.py
pronto/definition.py
pronto/metadata.py
pronto/ontology.py
pronto/pv.py
pronto/py.typed
pronto/relationship.py
pronto/synonym.py
pronto/term.py
pronto/xref.py
pronto/entity/__init__.py
pronto/entity/attributes.py
pronto/logic/__init__.py
pronto/logic/lineage.py
pronto/parsers/__init__.py
pronto/parsers/_fastobo.py
pronto/parsers/base.py
pronto/parsers/obo.py
pronto/parsers/obojson.py
pronto/parsers/rdfxml.py
pronto/serializers/__init__.py
pronto/serializers/_fastobo.py
pronto/serializers/base.py
pronto/serializers/obo.py
pronto/serializers/obojson.py
pronto/serializers/ofn.py
pronto/serializers/owx.py
pronto/serializers/rdfxml.py
pronto/utils/__init__.py
pronto/utils/io.py
pronto/utils/iter.py
pronto/utils/meta.py
pronto/utils/pool.py
pronto/utils/warnings.py
pronto-2.7.2.dist-info/licenses/COPYING
pronto-2.7.2.dist-info/METADATA
pronto-2.7.2.dist-info/WHEEL
pronto-2.7.2.dist-info/top_level.txt
pronto-2.7.2.dist-info/RECORD
