Metadata-Version: 2.4
Name: pronto
Version: 2.7.2
Summary: Python frontend to ontologies.
Author-email: Martin Larralde <martin.larralde@embl.de>
License: MIT License
Project-URL: Bug Tracker, https://github.com/althonos/pronto/issues
Project-URL: Changelog, https://pronto.readthedocs.io/en/latest/changes.html
Project-URL: Documentation, https://pronto.readthedocs.io/en/latest/
Project-URL: Coverage, https://app.codecov.io/gh/althonos/pronto
Project-URL: CI, https://github.com/althonos/pronto/actions
Keywords: bioinformatics,ontology,OBO,OWL
Classifier: Development Status :: 5 - Production/Stable
Classifier: Intended Audience :: Developers
Classifier: Intended Audience :: Science/Research
Classifier: Intended Audience :: Healthcare Industry
Classifier: License :: OSI Approved :: MIT License
Classifier: Operating System :: OS Independent
Classifier: Programming Language :: Python :: 3.7
Classifier: Programming Language :: Python :: 3.8
Classifier: Programming Language :: Python :: 3.9
Classifier: Programming Language :: Python :: 3.10
Classifier: Programming Language :: Python :: 3.11
Classifier: Programming Language :: Python :: 3.12
Classifier: Programming Language :: Python :: 3.13
Classifier: Programming Language :: Python :: 3.14
Classifier: Programming Language :: Python :: Implementation :: CPython
Classifier: Programming Language :: Python :: Implementation :: PyPy
Classifier: Topic :: Scientific/Engineering :: Bio-Informatics
Classifier: Topic :: Scientific/Engineering :: Medical Science Apps.
Classifier: Topic :: Software Development :: Libraries :: Python Modules
Classifier: Typing :: Typed
Requires-Python: >=3.7
License-File: COPYING
Requires-Dist: chardet~=5.0
Requires-Dist: fastobo<0.15.0,>=0.13.0
Requires-Dist: networkx<4.0,>=2.3
Requires-Dist: python-dateutil~=2.8
Dynamic: license-file
